MANIFEST.in
README.rst
setup.py
Flask_CouchDB_Schematics.egg-info/PKG-INFO
Flask_CouchDB_Schematics.egg-info/SOURCES.txt
Flask_CouchDB_Schematics.egg-info/dependency_links.txt
Flask_CouchDB_Schematics.egg-info/not-zip-safe
Flask_CouchDB_Schematics.egg-info/requires.txt
Flask_CouchDB_Schematics.egg-info/top_level.txt
flask_couchdb/__init__.py
flask_couchdb/document.py
flask_couchdb/manager.py
flask_couchdb/pagination.py
flask_couchdb/schematics_document.py
flask_couchdb/views.py
tests/test_flask_couchdb.py
tests/test_flask_couchdb_schematics.py