Metadata-Version: 1.0
Name: Flask-CouchDB-Schematics
Version: 1.0.0
Summary: Provides utilities for using CouchDB + Schematics with Flask
Home-page: http://github.com/ryanolson/flask-couchdb-schematics/
Author: Ryan Olson
Author-email: rmolson@gmail.com
License: MIT
Platform: any
